{
    "Category:2026 beginnings": "تصنيف:بدايات 2026",
    "Category:1686 beginnings": "تصنيف:بدايات 1686",
    "Category:1687 beginnings": "تصنيف:بدايات 1687",
    "Category:1688 beginnings": "تصنيف:بدايات 1688",
    "Category:1689 beginnings": "تصنيف:بدايات 1689",
    "Category:1690 beginnings": "تصنيف:بدايات 1690",
    "Category:1690s beginnings": "تصنيف:بدايات عقد 1690",
    "Category:1691 beginnings": "تصنيف:بدايات 1691",
    "Category:1692 beginnings": "تصنيف:بدايات 1692",
    "Category:1693 beginnings": "تصنيف:بدايات 1693",
    "Category:1694 beginnings": "تصنيف:بدايات 1694",
    "Category:1695 beginnings": "تصنيف:بدايات 1695",
    "Category:1696 beginnings": "تصنيف:بدايات 1696",
    "Category:1697 beginnings": "تصنيف:بدايات 1697",
    "Category:1698 beginnings": "تصنيف:بدايات 1698",
    "Category:1699 beginnings": "تصنيف:بدايات 1699",
    "Category:1501 beginnings": "تصنيف:بدايات 1501",
    "Category:1502 beginnings": "تصنيف:بدايات 1502",
    "Category:1503 beginnings": "تصنيف:بدايات 1503",
    "Category:1504 beginnings": "تصنيف:بدايات 1504",
    "Category:1505 beginnings": "تصنيف:بدايات 1505",
    "Category:1506 beginnings": "تصنيف:بدايات 1506",
    "Category:1507 beginnings": "تصنيف:بدايات 1507",
    "Category:1508 beginnings": "تصنيف:بدايات 1508",
    "Category:1509 beginnings": "تصنيف:بدايات 1509",
    "Category:1510 beginnings": "تصنيف:بدايات 1510",
    "Category:1510s beginnings": "تصنيف:بدايات عقد 1510",
    "Category:1511 beginnings": "تصنيف:بدايات 1511",
    "Category:1512 beginnings": "تصنيف:بدايات 1512",
    "Category:1513 beginnings": "تصنيف:بدايات 1513",
    "Category:1514 beginnings": "تصنيف:بدايات 1514",
    "Category:1515 beginnings": "تصنيف:بدايات 1515",
    "Category:1516 beginnings": "تصنيف:بدايات 1516",
    "Category:1517 beginnings": "تصنيف:بدايات 1517",
    "Category:1518 beginnings": "تصنيف:بدايات 1518",
    "Category:1519 beginnings": "تصنيف:بدايات 1519",
    "Category:1520 beginnings": "تصنيف:بدايات 1520",
    "Category:1520s beginnings": "تصنيف:بدايات عقد 1520",
    "Category:1521 beginnings": "تصنيف:بدايات 1521",
    "Category:1522 beginnings": "تصنيف:بدايات 1522",
    "Category:1523 beginnings": "تصنيف:بدايات 1523",
    "Category:1524 beginnings": "تصنيف:بدايات 1524",
    "Category:1525 beginnings": "تصنيف:بدايات 1525",
    "Category:1526 beginnings": "تصنيف:بدايات 1526",
    "Category:1527 beginnings": "تصنيف:بدايات 1527",
    "Category:1528 beginnings": "تصنيف:بدايات 1528",
    "Category:1529 beginnings": "تصنيف:بدايات 1529",
    "Category:1530 beginnings": "تصنيف:بدايات 1530",
    "Category:1530s beginnings": "تصنيف:بدايات عقد 1530",
    "Category:1531 beginnings": "تصنيف:بدايات 1531",
    "Category:1532 beginnings": "تصنيف:بدايات 1532",
    "Category:1533 beginnings": "تصنيف:بدايات 1533",
    "Category:1534 beginnings": "تصنيف:بدايات 1534",
    "Category:1535 beginnings": "تصنيف:بدايات 1535",
    "Category:1536 beginnings": "تصنيف:بدايات 1536",
    "Category:1537 beginnings": "تصنيف:بدايات 1537",
    "Category:1538 beginnings": "تصنيف:بدايات 1538",
    "Category:1539 beginnings": "تصنيف:بدايات 1539",
    "Category:1540 beginnings": "تصنيف:بدايات 1540",
    "Category:1540s beginnings": "تصنيف:بدايات عقد 1540",
    "Category:1541 beginnings": "تصنيف:بدايات 1541",
    "Category:1542 beginnings": "تصنيف:بدايات 1542",
    "Category:1543 beginnings": "تصنيف:بدايات 1543",
    "Category:1544 beginnings": "تصنيف:بدايات 1544",
    "Category:1545 beginnings": "تصنيف:بدايات 1545",
    "Category:1546 beginnings": "تصنيف:بدايات 1546",
    "Category:1547 beginnings": "تصنيف:بدايات 1547",
    "Category:1548 beginnings": "تصنيف:بدايات 1548",
    "Category:1549 beginnings": "تصنيف:بدايات 1549",
    "Category:1550 beginnings": "تصنيف:بدايات 1550",
    "Category:1550s beginnings": "تصنيف:بدايات عقد 1550",
    "Category:1551 beginnings": "تصنيف:بدايات 1551",
    "Category:1552 beginnings": "تصنيف:بدايات 1552",
    "Category:1553 beginnings": "تصنيف:بدايات 1553",
    "Category:1554 beginnings": "تصنيف:بدايات 1554",
    "Category:1555 beginnings": "تصنيف:بدايات 1555",
    "Category:1556 beginnings": "تصنيف:بدايات 1556",
    "Category:1557 beginnings": "تصنيف:بدايات 1557",
    "Category:1558 beginnings": "تصنيف:بدايات 1558",
    "Category:1559 beginnings": "تصنيف:بدايات 1559",
    "Category:1560 beginnings": "تصنيف:بدايات 1560",
    "Category:1560s beginnings": "تصنيف:بدايات عقد 1560",
    "Category:1561 beginnings": "تصنيف:بدايات 1561",
    "Category:1562 beginnings": "تصنيف:بدايات 1562",
    "Category:1563 beginnings": "تصنيف:بدايات 1563",
    "Category:1564 beginnings": "تصنيف:بدايات 1564",
    "Category:1565 beginnings": "تصنيف:بدايات 1565",
    "Category:1566 beginnings": "تصنيف:بدايات 1566",
    "Category:1567 beginnings": "تصنيف:بدايات 1567",
    "Category:1568 beginnings": "تصنيف:بدايات 1568",
    "Category:1569 beginnings": "تصنيف:بدايات 1569",
    "Category:1570 beginnings": "تصنيف:بدايات 1570",
    "Category:1570s beginnings": "تصنيف:بدايات عقد 1570",
    "Category:1571 beginnings": "تصنيف:بدايات 1571",
    "Category:1572 beginnings": "تصنيف:بدايات 1572",
    "Category:1573 beginnings": "تصنيف:بدايات 1573",
    "Category:1574 beginnings": "تصنيف:بدايات 1574",
    "Category:1575 beginnings": "تصنيف:بدايات 1575",
    "Category:1576 beginnings": "تصنيف:بدايات 1576",
    "Category:1577 beginnings": "تصنيف:بدايات 1577",
    "Category:1578 beginnings": "تصنيف:بدايات 1578",
    "Category:1579 beginnings": "تصنيف:بدايات 1579",
    "Category:1580 beginnings": "تصنيف:بدايات 1580",
    "Category:1580s beginnings": "تصنيف:بدايات عقد 1580",
    "Category:1581 beginnings": "تصنيف:بدايات 1581",
    "Category:1582 beginnings": "تصنيف:بدايات 1582",
    "Category:1583 beginnings": "تصنيف:بدايات 1583",
    "Category:1584 beginnings": "تصنيف:بدايات 1584",
    "Category:1585 beginnings": "تصنيف:بدايات 1585",
    "Category:1586 beginnings": "تصنيف:بدايات 1586",
    "Category:1587 beginnings": "تصنيف:بدايات 1587",
    "Category:1588 beginnings": "تصنيف:بدايات 1588",
    "Category:1589 beginnings": "تصنيف:بدايات 1589",
    "Category:1590 beginnings": "تصنيف:بدايات 1590",
    "Category:1590s beginnings": "تصنيف:بدايات عقد 1590",
    "Category:1591 beginnings": "تصنيف:بدايات 1591",
    "Category:1592 beginnings": "تصنيف:بدايات 1592",
    "Category:1593 beginnings": "تصنيف:بدايات 1593",
    "Category:1594 beginnings": "تصنيف:بدايات 1594",
    "Category:1595 beginnings": "تصنيف:بدايات 1595",
    "Category:1596 beginnings": "تصنيف:بدايات 1596",
    "Category:1597 beginnings": "تصنيف:بدايات 1597",
    "Category:1598 beginnings": "تصنيف:بدايات 1598",
    "Category:1599 beginnings": "تصنيف:بدايات 1599",
    "Category:1605 beginnings": "تصنيف:بدايات 1605",
    "Category:1606 beginnings": "تصنيف:بدايات 1606",
    "Category:1607 beginnings": "تصنيف:بدايات 1607",
    "Category:1608 beginnings": "تصنيف:بدايات 1608",
    "Category:1609 beginnings": "تصنيف:بدايات 1609",
    "Category:1610 beginnings": "تصنيف:بدايات 1610",
    "Category:1610s beginnings": "تصنيف:بدايات عقد 1610",
    "Category:1611 beginnings": "تصنيف:بدايات 1611",
    "Category:1612 beginnings": "تصنيف:بدايات 1612",
    "Category:1613 beginnings": "تصنيف:بدايات 1613",
    "Category:1614 beginnings": "تصنيف:بدايات 1614",
    "Category:1615 beginnings": "تصنيف:بدايات 1615",
    "Category:1616 beginnings": "تصنيف:بدايات 1616",
    "Category:1617 beginnings": "تصنيف:بدايات 1617",
    "Category:1618 beginnings": "تصنيف:بدايات 1618",
    "Category:1619 beginnings": "تصنيف:بدايات 1619",
    "Category:1620 beginnings": "تصنيف:بدايات 1620",
    "Category:1620s beginnings": "تصنيف:بدايات عقد 1620",
    "Category:1621 beginnings": "تصنيف:بدايات 1621",
    "Category:1622 beginnings": "تصنيف:بدايات 1622",
    "Category:1623 beginnings": "تصنيف:بدايات 1623",
    "Category:1624 beginnings": "تصنيف:بدايات 1624",
    "Category:1625 beginnings": "تصنيف:بدايات 1625",
    "Category:1626 beginnings": "تصنيف:بدايات 1626",
    "Category:1627 beginnings": "تصنيف:بدايات 1627",
    "Category:1628 beginnings": "تصنيف:بدايات 1628",
    "Category:1629 beginnings": "تصنيف:بدايات 1629",
    "Category:1630 beginnings": "تصنيف:بدايات 1630",
    "Category:1630s beginnings": "تصنيف:بدايات عقد 1630",
    "Category:1631 beginnings": "تصنيف:بدايات 1631",
    "Category:1632 beginnings": "تصنيف:بدايات 1632",
    "Category:1633 beginnings": "تصنيف:بدايات 1633",
    "Category:1634 beginnings": "تصنيف:بدايات 1634",
    "Category:1635 beginnings": "تصنيف:بدايات 1635",
    "Category:1636 beginnings": "تصنيف:بدايات 1636",
    "Category:1637 beginnings": "تصنيف:بدايات 1637",
    "Category:1638 beginnings": "تصنيف:بدايات 1638",
    "Category:1639 beginnings": "تصنيف:بدايات 1639",
    "Category:1671 beginnings": "تصنيف:بدايات 1671",
    "Category:1672 beginnings": "تصنيف:بدايات 1672",
    "Category:1673 beginnings": "تصنيف:بدايات 1673",
    "Category:1674 beginnings": "تصنيف:بدايات 1674",
    "Category:1675 beginnings": "تصنيف:بدايات 1675",
    "Category:1676 beginnings": "تصنيف:بدايات 1676",
    "Category:1677 beginnings": "تصنيف:بدايات 1677",
    "Category:1678 beginnings": "تصنيف:بدايات 1678",
    "Category:1679 beginnings": "تصنيف:بدايات 1679",
    "Category:1680 beginnings": "تصنيف:بدايات 1680",
    "Category:1680s beginnings": "تصنيف:بدايات عقد 1680",
    "Category:1681 beginnings": "تصنيف:بدايات 1681",
    "Category:1682 beginnings": "تصنيف:بدايات 1682",
    "Category:1683 beginnings": "تصنيف:بدايات 1683",
    "Category:1684 beginnings": "تصنيف:بدايات 1684",
    "Category:1685 beginnings": "تصنيف:بدايات 1685",
    "Category:1640 beginnings": "تصنيف:بدايات 1640",
    "Category:1640s beginnings": "تصنيف:بدايات عقد 1640",
    "Category:1641 beginnings": "تصنيف:بدايات 1641",
    "Category:1642 beginnings": "تصنيف:بدايات 1642",
    "Category:1643 beginnings": "تصنيف:بدايات 1643",
    "Category:1644 beginnings": "تصنيف:بدايات 1644",
    "Category:1645 beginnings": "تصنيف:بدايات 1645",
    "Category:1646 beginnings": "تصنيف:بدايات 1646",
    "Category:1647 beginnings": "تصنيف:بدايات 1647",
    "Category:1648 beginnings": "تصنيف:بدايات 1648",
    "Category:1649 beginnings": "تصنيف:بدايات 1649",
    "Category:1650 beginnings": "تصنيف:بدايات 1650",
    "Category:1650s beginnings": "تصنيف:بدايات عقد 1650",
    "Category:1651 beginnings": "تصنيف:بدايات 1651",
    "Category:1652 beginnings": "تصنيف:بدايات 1652",
    "Category:1653 beginnings": "تصنيف:بدايات 1653",
    "Category:1654 beginnings": "تصنيف:بدايات 1654",
    "Category:1655 beginnings": "تصنيف:بدايات 1655"
}